README.md
setup.py
fileMapping/__init__.py
fileMapping/plugIns.py
fileMapping/pluginLoading.py
fileMapping/register.py
fileMapping/string.py
fileMapping.egg-info/PKG-INFO
fileMapping.egg-info/SOURCES.txt
fileMapping.egg-info/dependency_links.txt
fileMapping.egg-info/top_level.txt
fileMapping/helperFunctions_expansion/__init__.py
fileMapping/helperFunctions_expansion/empty.py
fileMapping/helperFunctions_expansion/helperFunctions.py
fileMapping/helperFunctions_expansion/informationProcessing.py
fileMapping/helperFunctions_expansion/multithreading.py
fileMapping/helperFunctions_expansion/multithreading_v32.py
fileMapping/helperFunctions_expansion/parameterApplication.py
fileMapping/information/__init__.py
fileMapping/information/config.py
fileMapping/information/error.py
fileMapping/information/fileMappingConfig.py
fileMapping/information/plugins.py
fileMapping/method/__init__.py
fileMapping/method/fileOperations.py
fileMapping/multithreading_fileMapping/__init__.py
fileMapping/multithreading_fileMapping/fileMapping_func.py
fileMapping/server/__init__.py
fileMapping/server/small.py