Metadata-Version: 2.1
Name: fileMapping
Version: 0.3.21
Summary: 用于快速调用文件夹下的py文件或者包
Home-page: https://github.com/bop-lp/fileMapping
Author: 朝歌夜弦
Author-email: bop-lp@qq.com
